TeleSocketClient/__init__.py
TeleSocketClient/exceptions.py
TeleSocketClient/json_helper.py
TeleSocketClient/manager.py
TeleSocketClient/request.py
TeleSocketClient/types.py
TeleSocketClient/bin/__init__.py
TeleSocketClient/bin/cli.py
TeleSocketClient-0.1.3b1.dist-info/DESCRIPTION.rst
TeleSocketClient-0.1.3b1.dist-info/METADATA
TeleSocketClient-0.1.3b1.dist-info/RECORD
TeleSocketClient-0.1.3b1.dist-info/WHEEL
TeleSocketClient-0.1.3b1.dist-info/metadata.json
TeleSocketClient-0.1.3b1.dist-info/top_level.txt
